Metadata-Version: 2.1
Name: effdet
Version: 0.4.1
Summary: EfficientDet for PyTorch
Home-page: https://github.com/rwightman/efficientdet-pytorch
Author: Ross Wightman
Author-email: hello@rwightman.com
Keywords: pytorch pretrained efficientdet efficientnet bifpn object detection
Classifier: Development Status :: 3 - Alpha
Classifier: Intended Audience :: Education
Classifier: Intended Audience :: Science/Research
Classifier: License :: OSI Approved :: Apache Software License
Classifier: Programming Language :: Python :: 3.7
Classifier: Programming Language :: Python :: 3.8
Classifier: Programming Language :: Python :: 3.9
Classifier: Programming Language :: Python :: 3.10
Classifier: Topic :: Scientific/Engineering
Classifier: Topic :: Scientific/Engineering :: Artificial Intelligence
Classifier: Topic :: Software Development
Classifier: Topic :: Software Development :: Libraries
Classifier: Topic :: Software Development :: Libraries :: Python Modules
Requires-Python: >=3.7
License-File: LICENSE
